odoo/addons/account_mass_reconcile_as_job/README.rst
odoo/addons/account_mass_reconcile_as_job/__init__.py
odoo/addons/account_mass_reconcile_as_job/__manifest__.py
odoo/addons/account_mass_reconcile_as_job/data/ir_config_parameter_data.xml
odoo/addons/account_mass_reconcile_as_job/data/queue_job_channel_data.xml
odoo/addons/account_mass_reconcile_as_job/data/queue_job_function_data.xml
odoo/addons/account_mass_reconcile_as_job/i18n/account_mass_reconcile_as_job.pot
odoo/addons/account_mass_reconcile_as_job/i18n/es.po
odoo/addons/account_mass_reconcile_as_job/i18n/sv.po
odoo/addons/account_mass_reconcile_as_job/models/__init__.py
odoo/addons/account_mass_reconcile_as_job/models/base_reconciliation.py
odoo/addons/account_mass_reconcile_as_job/models/mass_reconcile.py
odoo/addons/account_mass_reconcile_as_job/readme/CONTRIBUTORS.rst
odoo/addons/account_mass_reconcile_as_job/readme/CREDITS.rst
odoo/addons/account_mass_reconcile_as_job/readme/DESCRIPTION.rst
odoo/addons/account_mass_reconcile_as_job/readme/USAGE.rst
odoo/addons/account_mass_reconcile_as_job/static/description/icon.png
odoo/addons/account_mass_reconcile_as_job/static/description/index.html
odoo/addons/account_mass_reconcile_as_job/tests/__init__.py
odoo/addons/account_mass_reconcile_as_job/tests/test_mass_reconcile_as_job.py
odoo/addons/account_mass_reconcile_as_job/tests/test_scenario_reconcile_as_job.py
odoo14_addon_account_mass_reconcile_as_job-14.0.1.1.2.dist-info/METADATA
odoo14_addon_account_mass_reconcile_as_job-14.0.1.1.2.dist-info/WHEEL
odoo14_addon_account_mass_reconcile_as_job-14.0.1.1.2.dist-info/top_level.txt
odoo14_addon_account_mass_reconcile_as_job-14.0.1.1.2.dist-info/RECORD
